{
    "meta": {
        "limit": 1000,
        "next": null,
        "offset": 0,
        "previous": null,
        "total_count": 7
    },
    "objects": [{
        "absentee_and_provisional": false,
        "cong_dist_level": false,
        "cong_dist_level_status": "",
        "county_level": false,
        "county_level_status": "",
        "direct_link": "",
        "direct_links": ["http://sos.ga.gov/elections/election_results/2000_1128/"],
        "end_date": "2000-11-28",
        "gov": false,
        "house": false,
        "id": 1353,
        "organization": {
            "city": "Atlanta",
            "fec_page": "http://www.fec.gov/pubrec/cfsdd/gadir.htm",
            "gov_agency": true,
            "gov_level": "state",
            "id": 35,
            "name": "Georgia Secretary of State",
            "resource_uri": "/api/v1/organization/35/",
            "slug": "georgia-secretary-state",
            "state": "GA",
            "street": "214 State Capitol",
            "url": "http://www.sos.georgia.gov/"
        },
        "portal_link": "http://sos.ga.gov/elections/election_results/",
        "precinct_level": false,
        "precinct_level_status": "",
        "prez": false,
        "primary_note": "",
        "primary_type": "",
        "race_type": "general-runoff",
        "resource_uri": "/api/v1/election/1353/",
        "result_type": "certified",
        "senate": false,
        "special": false,
        "start_date": "2000-11-28",
        "state": {
            "name": "Georgia",
            "postal": "GA",
            "resource_uri": "/api/v1/state/GA/"
        },
        "state_leg": true,
        "state_leg_level": false,
        "state_leg_level_status": "",
        "state_level": true,
        "state_level_status": "yes",
        "state_officers": false,
        "user_fullname": ""
    }, {
        "absentee_and_provisional": false,
        "cong_dist_level": false,
        "cong_dist_level_status": "",
        "county_level": true,
        "county_level_status": "yes",
        "direct_link": "http://www.sos.ga.gov/elections/election_results/2000_1107/0000100.htm",
        "direct_links": [
            "http://sos.ga.gov/elections/election_results/2000_1107/summary.htm", 
            "http://sos.ga.gov/elections/election_results/2000_1107/0000100.htm", 
            "http://sos.ga.gov/elections/election_results/2000_1107/0000200.htm", 
            "http://sos.ga.gov/elections/election_results/2000_1107/0000300.htm", 
            "http://sos.ga.gov/elections/election_results/2000_1107/0000400.htm", 
            "http://sos.ga.gov/elections/election_results/2000_1107/0000500.htm", 
            "http://sos.ga.gov/elections/election_results/2000_1107/0000600.htm", 
            "http://sos.ga.gov/elections/election_results/2000_1107/0000700.htm", 
            "http://sos.ga.gov/elections/election_results/2000_1107/0000800.htm", 
            "http://sos.ga.gov/elections/election_results/2000_1107/0000900.htm", 
            "http://sos.ga.gov/elections/election_results/2000_1107/0001000.htm", 
            "http://sos.ga.gov/elections/election_results/2000_1107/0001100.htm", 
            "http://sos.ga.gov/elections/election_results/2000_1107/0001200.htm", 
            "http://sos.ga.gov/elections/election_results/2000_1107/0001300.htm", 
            "http://sos.ga.gov/elections/election_results/2000_1107/0001400.htm", 
            "http://sos.ga.gov/elections/election_results/2000_1107/0001500.htm"
            ],
        "end_date": "2000-11-07",
        "gov": false,
        "house": true,
        "id": 520,
        "organization": {
            "city": "Atlanta",
            "fec_page": "http://www.fec.gov/pubrec/cfsdd/gadir.htm",
            "gov_agency": true,
            "gov_level": "state",
            "id": 35,
            "name": "Georgia Secretary of State",
            "resource_uri": "/api/v1/organization/35/",
            "slug": "georgia-secretary-state",
            "state": "GA",
            "street": "214 State Capitol",
            "url": "http://www.sos.georgia.gov/"
        },
        "portal_link": "http://sos.ga.gov/elections/election_results/2000_1107/",
        "precinct_level": false,
        "precinct_level_status": "",
        "prez": true,
        "primary_note": "",
        "primary_type": "",
        "race_type": "general",
        "resource_uri": "/api/v1/election/520/",
        "result_type": "certified",
        "senate": true,
        "special": false,
        "start_date": "2000-11-07",
        "state": {
            "name": "Georgia",
            "postal": "GA",
            "resource_uri": "/api/v1/state/GA/"
        },
        "state_leg": false,
        "state_leg_level": false,
        "state_leg_level_status": "",
        "state_level": true,
        "state_level_status": "yes",
        "state_officers": false,
        "user_fullname": "Montanez, Luigi "
    }, {
        "absentee_and_provisional": false,
        "cong_dist_level": false,
        "cong_dist_level_status": "",
        "county_level": true,
        "county_level_status": "yes",
        "direct_link": "",
        "direct_links": [
            "http://sos.ga.gov/elections/election_results/2000_0808/0000910.htm", 
            "http://sos.ga.gov/elections/election_results/2000_0808/0004120.htm", 
            "http://sos.ga.gov/elections/election_results/2000_0808/0005320.htm", 
            "http://sos.ga.gov/elections/election_results/2000_0808/0007620.htm", 
            "http://sos.ga.gov/elections/election_results/2000_0808/0008810.htm", 
            "http://sos.ga.gov/elections/election_results/2000_0808/0009720.htm", 
            "http://sos.ga.gov/elections/election_results/2000_0808/0017820.htm", 
            "http://sos.ga.gov/elections/election_results/2000_0808/0022910.htm", 
            "http://sos.ga.gov/elections/election_results/2000_0808/0028310.htm", 
            "http://sos.ga.gov/elections/election_results/2000_0808/0036030.htm", 
            "http://sos.ga.gov/elections/election_results/2000_0808/0039830.htm", 
            "http://sos.ga.gov/elections/election_results/2000_0808/0041930.htm"
            ],
        "end_date": "2000-08-08",
        "gov": false,
        "house": true,
        "id": 1352,
        "organization": {
            "city": "Atlanta",
            "fec_page": "http://www.fec.gov/pubrec/cfsdd/gadir.htm",
            "gov_agency": true,
            "gov_level": "state",
            "id": 35,
            "name": "Georgia Secretary of State",
            "resource_uri": "/api/v1/organization/35/",
            "slug": "georgia-secretary-state",
            "state": "GA",
            "street": "214 State Capitol",
            "url": "http://www.sos.georgia.gov/"
        },
        "portal_link": "http://sos.ga.gov/elections/election_results/2000_0808/",
        "precinct_level": false,
        "precinct_level_status": "",
        "prez": false,
        "primary_note": "",
        "primary_type": "closed",
        "race_type": "primary-runoff",
        "resource_uri": "/api/v1/election/1352/",
        "result_type": "certified",
        "senate": false,
        "special": false,
        "start_date": "2000-08-08",
        "state": {
            "name": "Georgia",
            "postal": "GA",
            "resource_uri": "/api/v1/state/GA/"
        },
        "state_leg": true,
        "state_leg_level": false,
        "state_leg_level_status": "",
        "state_level": true,
        "state_level_status": "yes",
        "state_officers": false,
        "user_fullname": ""
    }, {
        "absentee_and_provisional": false,
        "cong_dist_level": false,
        "cong_dist_level_status": "",
        "county_level": true,
        "county_level_status": "yes",
        "direct_link": "",
        "direct_links": ["http://sos.ga.gov/elections/election_results/2000_0718/summary.htm"],
        "end_date": "2000-07-18",
        "gov": false,
        "house": true,
        "id": 1351,
        "organization": {
            "city": "Atlanta",
            "fec_page": "http://www.fec.gov/pubrec/cfsdd/gadir.htm",
            "gov_agency": true,
            "gov_level": "state",
            "id": 35,
            "name": "Georgia Secretary of State",
            "resource_uri": "/api/v1/organization/35/",
            "slug": "georgia-secretary-state",
            "state": "GA",
            "street": "214 State Capitol",
            "url": "http://www.sos.georgia.gov/"
        },
        "portal_link": "http://sos.ga.gov/elections/election_results/2000_0718/",
        "precinct_level": false,
        "precinct_level_status": "",
        "prez": false,
        "primary_note": "",
        "primary_type": "closed",
        "race_type": "primary",
        "resource_uri": "/api/v1/election/1351/",
        "result_type": "certified",
        "senate": true,
        "special": false,
        "start_date": "2000-07-18",
        "state": {
            "name": "Georgia",
            "postal": "GA",
            "resource_uri": "/api/v1/state/GA/"
        },
        "state_leg": true,
        "state_leg_level": false,
        "state_leg_level_status": "",
        "state_level": true,
        "state_level_status": "yes",
        "state_officers": false,
        "user_fullname": ""
    }, {
        "absentee_and_provisional": false,
        "cong_dist_level": false,
        "cong_dist_level_status": "",
        "county_level": true,
        "county_level_status": "yes",
        "direct_link": "http://www.sos.ga.gov/elections/election_results/2000_0307/0000110.htm",
        "direct_links": [
            "http://sos.ga.gov/elections/election_results/2000_0307/0000110.htm", 
            "http://sos.ga.gov/elections/election_results/2000_0307/0000120.htm", 
            "http://sos.ga.gov/elections/election_results/2000_0307/0000230.htm"
            ],
        "end_date": "2000-03-07",
        "gov": false,
        "house": false,
        "id": 551,
        "organization": {
            "city": "Atlanta",
            "fec_page": "http://www.fec.gov/pubrec/cfsdd/gadir.htm",
            "gov_agency": true,
            "gov_level": "state",
            "id": 35,
            "name": "Georgia Secretary of State",
            "resource_uri": "/api/v1/organization/35/",
            "slug": "georgia-secretary-state",
            "state": "GA",
            "street": "214 State Capitol",
            "url": "http://www.sos.georgia.gov/"
        },
        "portal_link": "http://www.sos.ga.gov/elections/election_results/",
        "precinct_level": false,
        "precinct_level_status": "",
        "prez": true,
        "primary_note": "",
        "primary_type": "open",
        "race_type": "primary",
        "resource_uri": "/api/v1/election/551/",
        "result_type": "certified",
        "senate": false,
        "special": false,
        "start_date": "2000-03-07",
        "state": {
            "name": "Georgia",
            "postal": "GA",
            "resource_uri": "/api/v1/state/GA/"
        },
        "state_leg": false,
        "state_leg_level": false,
        "state_leg_level_status": "",
        "state_level": true,
        "state_level_status": "yes",
        "state_officers": false,
        "user_fullname": "Montanez, Luigi "
    }, {
        "absentee_and_provisional": false,
        "cong_dist_level": false,
        "cong_dist_level_status": "",
        "county_level": false,
        "county_level_status": "",
        "direct_link": "",
        "direct_links": ["http://sos.ga.gov/elections/election_results/2000_0215/"],
        "end_date": "2000-02-15",
        "gov": false,
        "house": false,
        "id": 1350,
        "organization": {
            "city": "Atlanta",
            "fec_page": "http://www.fec.gov/pubrec/cfsdd/gadir.htm",
            "gov_agency": true,
            "gov_level": "state",
            "id": 35,
            "name": "Georgia Secretary of State",
            "resource_uri": "/api/v1/organization/35/",
            "slug": "georgia-secretary-state",
            "state": "GA",
            "street": "214 State Capitol",
            "url": "http://www.sos.georgia.gov/"
        },
        "portal_link": "http://sos.ga.gov/elections/election_results/",
        "precinct_level": false,
        "precinct_level_status": "",
        "prez": false,
        "primary_note": "",
        "primary_type": "",
        "race_type": "general",
        "resource_uri": "/api/v1/election/1350/",
        "result_type": "certified",
        "senate": false,
        "special": true,
        "start_date": "2000-02-15",
        "state": {
            "name": "Georgia",
            "postal": "GA",
            "resource_uri": "/api/v1/state/GA/"
        },
        "state_leg": true,
        "state_leg_level": false,
        "state_leg_level_status": "",
        "state_level": true,
        "state_level_status": "yes",
        "state_officers": false,
        "user_fullname": ""
    }, {
        "absentee_and_provisional": false,
        "cong_dist_level": false,
        "cong_dist_level_status": "",
        "county_level": false,
        "county_level_status": "",
        "direct_link": "",
        "direct_links": ["http://sos.ga.gov/elections/election_results/2000_0111/"],
        "end_date": "2000-01-11",
        "gov": false,
        "house": false,
        "id": 1349,
        "organization": {
            "city": "Atlanta",
            "fec_page": "http://www.fec.gov/pubrec/cfsdd/gadir.htm",
            "gov_agency": true,
            "gov_level": "state",
            "id": 35,
            "name": "Georgia Secretary of State",
            "resource_uri": "/api/v1/organization/35/",
            "slug": "georgia-secretary-state",
            "state": "GA",
            "street": "214 State Capitol",
            "url": "http://www.sos.georgia.gov/"
        },
        "portal_link": "http://sos.ga.gov/elections/election_results/",
        "precinct_level": false,
        "precinct_level_status": "",
        "prez": false,
        "primary_note": "",
        "primary_type": "",
        "race_type": "general-runoff",
        "resource_uri": "/api/v1/election/1349/",
        "result_type": "certified",
        "senate": false,
        "special": true,
        "start_date": "2000-01-11",
        "state": {
            "name": "Georgia",
            "postal": "GA",
            "resource_uri": "/api/v1/state/GA/"
        },
        "state_leg": true,
        "state_leg_level": false,
        "state_leg_level_status": "",
        "state_level": true,
        "state_level_status": "yes",
        "state_officers": false,
        "user_fullname": ""
    }]
}